registerit/__init__.py
registerit/build_and_upload.py
registerit/cli.py
registerit-0.2.0.dist-info/LICENSE.txt
registerit-0.2.0.dist-info/METADATA
registerit-0.2.0.dist-info/WHEEL
registerit-0.2.0.dist-info/entry_points.txt
registerit-0.2.0.dist-info/top_level.txt
registerit-0.2.0.dist-info/zip-safe
registerit-0.2.0.dist-info/RECORD
